NEMO_publications/__init__.py
NEMO_publications/admin.py
NEMO_publications/api.py
NEMO_publications/app_settings.py
NEMO_publications/apps.py
NEMO_publications/customization.py
NEMO_publications/forms.py
NEMO_publications/models.py
NEMO_publications/notifications.py
NEMO_publications/serializers.py
NEMO_publications/urls.py
NEMO_publications/utils.py
NEMO_publications/migrations/0001_initial.py
NEMO_publications/migrations/0002_publicationmetadata_month.py
NEMO_publications/migrations/0003_publicationmetadata_status_and_json.py
NEMO_publications/migrations/0004_publicationmetadata_image_url.py
NEMO_publications/migrations/0005_userpublicationstatus.py
NEMO_publications/migrations/0006_alter_userpublicationstatus_options.py
NEMO_publications/migrations/__init__.py
NEMO_publications/templates/NEMO_publications/carousel.html
NEMO_publications/templates/NEMO_publications/jumbotron.html
NEMO_publications/templates/NEMO_publications/leaderboard.html
NEMO_publications/templates/NEMO_publications/new_landing.html
NEMO_publications/templates/NEMO_publications/publication_data.html
NEMO_publications/templates/NEMO_publications/publication_metadata.html
NEMO_publications/templates/NEMO_publications/publication_search.html
NEMO_publications/templates/NEMO_publications/publication_thumbnail.html
NEMO_publications/templates/NEMO_publications/publications.html
NEMO_publications/templates/NEMO_publications/publications_base.html
NEMO_publications/templates/customizations/customizations_publications.html
NEMO_publications/tests/__init__.py
NEMO_publications/tests/test_clean_doi.py
NEMO_publications/tests/test_placeholder.py
NEMO_publications/tests/test_settings.py
NEMO_publications/views/__init__.py
NEMO_publications/views/publications.py
nemo_publications-1.4.9.dist-info/licenses/LICENSE
nemo_publications-1.4.9.dist-info/METADATA
nemo_publications-1.4.9.dist-info/WHEEL
nemo_publications-1.4.9.dist-info/top_level.txt
nemo_publications-1.4.9.dist-info/RECORD
