Metadata-Version: 2.4
Name: NEMO-publications
Version: 1.4.9
Summary: Plugin adding publications that users can submit and link to tools/projects using the DOI
Author-email: Atlantis Labs LLC <atlantis@atlantislabs.io>
License: MIT License
Project-URL: Homepage, https://gitlab.com/nemo-community/atlantis-labs/nemo-publications
Project-URL: Changelog, https://gitlab.com/nemo-community/atlantis-labs/nemo-publications/-/releases
Project-URL: Issues, https://gitlab.com/nemo-community/atlantis-labs/nemo-publications/-/issues
Project-URL: CI, https://gitlab.com/nemo-community/atlantis-labs/nemo-publications/-/pipelines
Keywords: NEMO
Classifier: Development Status :: 5 - Production/Stable
Classifier: Intended Audience :: Developers
Classifier: License :: OSI Approved :: MIT License
Classifier: Framework :: Django :: 4.2
Classifier: Programming Language :: Python :: 3.9
Classifier: Programming Language :: Python :: 3.10
Classifier: Programming Language :: Python :: 3.11
Classifier: Programming Language :: Python :: 3.12
Classifier: Programming Language :: Python :: 3.13
Requires-Python: >=3.9
License-File: LICENSE
Requires-Dist: django
Requires-Dist: bibtexparser
Requires-Dist: python-dateutil
Requires-Dist: requests
Provides-Extra: nemo-ce
Requires-Dist: NEMO-CE>=7.0.0; extra == "nemo-ce"
Provides-Extra: nemo
Requires-Dist: NEMO>=7.0.0; extra == "nemo"
Provides-Extra: dev-tools
Requires-Dist: pre-commit; extra == "dev-tools"
Requires-Dist: djlint; extra == "dev-tools"
Requires-Dist: black; extra == "dev-tools"
Dynamic: license-file
